MANIFEST.in
README.md
requirements.txt
setup.cfg
setup.py
julpyter/__init__.py
julpyter/challenge.py
julpyter/challenges.py
julpyter/exporter.py
julpyter.egg-info/PKG-INFO
julpyter.egg-info/SOURCES.txt
julpyter.egg-info/dependency_links.txt
julpyter.egg-info/entry_points.txt
julpyter.egg-info/requires.txt
julpyter.egg-info/top_level.txt