Metadata-Version: 1.1
Name: julpyter
Version: 0.0.2
Summary: A python package which converts a jupyter notebook to a Galvanize Learn challenge
Home-page: https://github.com/embanner/julpyter
Author: Edward Banner
Author-email: edward.banner@galvanize.com
License: BSD
Download-URL: https://github.com/embanner/julpyter/tarball/0.0.2
Platform: UNKNOWN
Classifier: Development Status :: 3 - Alpha
Classifier: Intended Audience :: Developers
Classifier: Programming Language :: Python :: 3
